[
    {
        "src_node": "pitch black",
        "dst_node": "Bedroom",
        "num_paths": 1,
        "path_min_cutoffs": [
            1
        ],
        "id": "cad0ef762a26c8c8ca490eb096b7ffb2e70b46641efd17c3e02b6e5dc7e5d383"
    },
    {
        "src_node": "pitch black",
        "dst_node": "Country Lane",
        "num_paths": 1,
        "path_min_cutoffs": [
            19
        ],
        "id": "34a30e3ffd835dcfe0b9b2cb5d8bbe787ec4f3281a2e6ace5ec001f9d1476582"
    },
    {
        "src_node": "pitch black",
        "dst_node": "Dark",
        "num_paths": 1,
        "path_min_cutoffs": [
            38
        ],
        "id": "8b88f48f99e8af7c87b39d73e3b2f4b8d85f6a11c450e4f7b73e06467e0d8697"
    },
    {
        "src_node": "pitch black",
        "dst_node": "Front of House",
        "num_paths": 1,
        "path_min_cutoffs": [
            10
        ],
        "id": "b95f5f60563152bdb37734e6f892a5293b6f7014eca19c20b54f251dd06c38d0"
    },
    {
        "src_node": "pitch black",
        "dst_node": "Front Porch",
        "num_paths": 1,
        "path_min_cutoffs": [
            8
        ],
        "id": "d483f23be65f9a9b4fd6bee4b9099158fc2d5cd862bd7f0b24f13ebc92b77ce9"
    },
    {
        "src_node": "pitch black",
        "dst_node": "Captain's Quarters, in the poetry appreciation chair",
        "num_paths": 1,
        "path_min_cutoffs": [
            59
        ],
        "id": "455ba799669f1277ad2867e5c2acf8b44a76775748aa4de3fec00ccf6fa5ff97"
    },
    {
        "src_node": "pitch black",
        "dst_node": "Pub",
        "num_paths": 1,
        "path_min_cutoffs": [
            20
        ],
        "id": "cfe55fe06c0fd32ef3d5373dd4f4e5d0cb2ee1085d41ac3b04051f7cc91fc38a"
    },
    {
        "src_node": "pitch black",
        "dst_node": "Vogon Hold",
        "num_paths": 1,
        "path_min_cutoffs": [
            44
        ],
        "id": "2294063198a1dc61a3e16375fd9cbe1ae8fc4a23c306ef2608f9051ca1151e50"
    },
    {
        "src_node": "Bedroom",
        "dst_node": "Country Lane",
        "num_paths": 1,
        "path_min_cutoffs": [
            19
        ],
        "id": "1575728cde1cca54b54bed39abb4f1889a618012599e3bb505e279194195b9a6"
    },
    {
        "src_node": "Bedroom",
        "dst_node": "Dark",
        "num_paths": 1,
        "path_min_cutoffs": [
            38
        ],
        "id": "f2575347f44f35d140b494e4753219c69976decc697f31461f76d38bc5b5d622"
    },
    {
        "src_node": "Bedroom",
        "dst_node": "Front of House",
        "num_paths": 1,
        "path_min_cutoffs": [
            10
        ],
        "id": "082c4a952c3c3f4dfc21b67b021a71c8ea646bc911f1815c02e9314722c21695"
    },
    {
        "src_node": "Bedroom",
        "dst_node": "Front Porch",
        "num_paths": 1,
        "path_min_cutoffs": [
            8
        ],
        "id": "90447542f250793201b63e60b7c1d9b42c0f963ac53069333a9d311f550e015b"
    },
    {
        "src_node": "Bedroom",
        "dst_node": "Captain's Quarters, in the poetry appreciation chair",
        "num_paths": 1,
        "path_min_cutoffs": [
            59
        ],
        "id": "b9251ad7f177116cb481863592eafae3b80c9165a8de3c05c663ad13a2caa03c"
    },
    {
        "src_node": "Bedroom",
        "dst_node": "Pub",
        "num_paths": 1,
        "path_min_cutoffs": [
            20
        ],
        "id": "fc0233c2fe439616bd90faa5d646d5a16f4c2c0f95afe4142f7210b76f603241"
    },
    {
        "src_node": "Bedroom",
        "dst_node": "Vogon Hold",
        "num_paths": 1,
        "path_min_cutoffs": [
            44
        ],
        "id": "22606f7ac8e11e1989d68f8e847ddae7ac236eba5406d7820037a4379e5a145b"
    },
    {
        "src_node": "Country Lane",
        "dst_node": "Dark",
        "num_paths": 1,
        "path_min_cutoffs": [
            38
        ],
        "id": "17644330a34423281103013535fe342683d30d8f7e9f1f90547ad79cb21e8512"
    },
    {
        "src_node": "Country Lane",
        "dst_node": "Captain's Quarters, in the poetry appreciation chair",
        "num_paths": 1,
        "path_min_cutoffs": [
            59
        ],
        "id": "a8fb1a4729d442cc220a732a8807992f86b48e865f75adc76f82b1267b486b3e"
    },
    {
        "src_node": "Country Lane",
        "dst_node": "Pub",
        "num_paths": 1,
        "path_min_cutoffs": [
            20
        ],
        "id": "ff909a59ab6fce20c830048db3eed37a5e06d836015abfc0f069e5d09930dff8"
    },
    {
        "src_node": "Country Lane",
        "dst_node": "Vogon Hold",
        "num_paths": 1,
        "path_min_cutoffs": [
            44
        ],
        "id": "17e596885a294e96401512dc91a1d3b3c872fa62885d31fb941611423983dccf"
    },
    {
        "src_node": "Dark",
        "dst_node": "Captain's Quarters, in the poetry appreciation chair",
        "num_paths": 1,
        "path_min_cutoffs": [
            59
        ],
        "id": "911bc376b933403c064c4345d20109bc69fac54d84bfb9f4096b5c8004f8732e"
    },
    {
        "src_node": "Dark",
        "dst_node": "Vogon Hold",
        "num_paths": 1,
        "path_min_cutoffs": [
            44
        ],
        "id": "924c57720cd19361e76c579259e319c65d4afba8f8c2403e39649957dd50b535"
    },
    {
        "src_node": "Front of House",
        "dst_node": "Country Lane",
        "num_paths": 1,
        "path_min_cutoffs": [
            19
        ],
        "id": "87b32d69cb44f30d1f57b59ed0282c71001ca19e1867b078c7ef53aede483ff0"
    },
    {
        "src_node": "Front of House",
        "dst_node": "Dark",
        "num_paths": 1,
        "path_min_cutoffs": [
            38
        ],
        "id": "c0d859217baa0d34f2cfa2149086a288463452b7bc96f01de85c23c2cb4d495b"
    },
    {
        "src_node": "Front of House",
        "dst_node": "Captain's Quarters, in the poetry appreciation chair",
        "num_paths": 1,
        "path_min_cutoffs": [
            59
        ],
        "id": "de60c87b8267ee53b1567a644974adcc930a85d857b46f16f1985d8e7cff45f8"
    },
    {
        "src_node": "Front of House",
        "dst_node": "Pub",
        "num_paths": 1,
        "path_min_cutoffs": [
            20
        ],
        "id": "dd21699ab4eea8c1c7ca1236ef19092dd0fbbb92568e55ec983f03161c7bfeb3"
    },
    {
        "src_node": "Front of House",
        "dst_node": "Vogon Hold",
        "num_paths": 1,
        "path_min_cutoffs": [
            44
        ],
        "id": "8434eb26a3016bf1e6a0f6a40d79cc7316447fc51d53f54b83cd4444c26d7a6f"
    },
    {
        "src_node": "Front Porch",
        "dst_node": "Bedroom",
        "num_paths": 1,
        "path_min_cutoffs": [
            8
        ],
        "id": "2a308e3713182b5ef4414087de2cccb9d5eced74cea805395bea94927ddc13ed"
    },
    {
        "src_node": "Front Porch",
        "dst_node": "Country Lane",
        "num_paths": 1,
        "path_min_cutoffs": [
            19
        ],
        "id": "81bf0ac46e537181ee130db84f30ba3eeee049e8154a6691e92ec5579cb43d20"
    },
    {
        "src_node": "Front Porch",
        "dst_node": "Dark",
        "num_paths": 1,
        "path_min_cutoffs": [
            38
        ],
        "id": "50b669cd011903fc799ea3f9d5e7fe0f7513f3b5178697598a892fc7719d2f91"
    },
    {
        "src_node": "Front Porch",
        "dst_node": "Front of House",
        "num_paths": 1,
        "path_min_cutoffs": [
            10
        ],
        "id": "7ca90beea7a63abe99126d3a1a63f3e025f2d49a6653aed1772b48bc823527dd"
    },
    {
        "src_node": "Front Porch",
        "dst_node": "Captain's Quarters, in the poetry appreciation chair",
        "num_paths": 1,
        "path_min_cutoffs": [
            59
        ],
        "id": "1dd60bbef1938d502cd8b0f0d16bb38bd7002a16c1b35439e7a46b2cfa7a090e"
    },
    {
        "src_node": "Front Porch",
        "dst_node": "Pub",
        "num_paths": 1,
        "path_min_cutoffs": [
            20
        ],
        "id": "c10f53ebcfb0aa1c6ba62e031a4d0b1a3f9051df3cb5b8eb8005fd46ed08652d"
    },
    {
        "src_node": "Front Porch",
        "dst_node": "Vogon Hold",
        "num_paths": 1,
        "path_min_cutoffs": [
            44
        ],
        "id": "bc1f08fcd7b22c12f01d16db2f53993b7e296276e5bece5101f788eb0d29f96f"
    },
    {
        "src_node": "Captain's Quarters, in the poetry appreciation chair",
        "dst_node": "Vogon Hold",
        "num_paths": 1,
        "path_min_cutoffs": [
            70
        ],
        "id": "545000bdb2b5d93484e51e7809f85e67df4d4ccddeea196ec054b497955d3c57"
    },
    {
        "src_node": "Pub",
        "dst_node": "Country Lane",
        "num_paths": 1,
        "path_min_cutoffs": [
            26
        ],
        "id": "f0afb0ab258b81ae4e13a60c5fbf96672bb2edeb727862067144d44b00c0226a"
    },
    {
        "src_node": "Pub",
        "dst_node": "Dark",
        "num_paths": 1,
        "path_min_cutoffs": [
            38
        ],
        "id": "f4e9bf78aaa37fc62920de17ee917ea929a28dd14f1d1b954a9bbe14a4422bc5"
    },
    {
        "src_node": "Pub",
        "dst_node": "Captain's Quarters, in the poetry appreciation chair",
        "num_paths": 1,
        "path_min_cutoffs": [
            59
        ],
        "id": "f382d7ef9e9a25baf023649a9a14de41abbcf690367df09a6619fd566b0c3c52"
    },
    {
        "src_node": "Pub",
        "dst_node": "Vogon Hold",
        "num_paths": 1,
        "path_min_cutoffs": [
            44
        ],
        "id": "bae56c494f3f0582908ee0d97074898b86774cfa1eed781774af5a31ed91f332"
    },
    {
        "src_node": "Vogon Hold",
        "dst_node": "Captain's Quarters, in the poetry appreciation chair",
        "num_paths": 1,
        "path_min_cutoffs": [
            59
        ],
        "id": "d2792b66acabdcda268ca03287b8cefbdfd8908a8b5c81c7884c146a84ad48cf"
    }
]