{
    "north part": [
        "north part (obj104)"
    ],
    "lab center": [
        "lab center (obj77)"
    ],
    "east part": [
        "east part (obj101)"
    ],
    "corridor": [
        "corridor (obj96)"
    ],
    "Kemp's office": [
        "kemp's office (obj182)"
    ],
    "south part": [
        "south part (obj86)"
    ],
    "north walkway": [
        "north walkway (obj72)"
    ],
    "west walkway": [
        "west walkway (obj70)"
    ],
    "SCIMITAR": [
        "scimitar (obj249)"
    ],
    "crawl space": [
        "crawl space (obj237)"
    ],
    "docking tank": [
        "docking tank (obj163)"
    ],
    "docking tank entrance": [
        "docking entrance (obj159)"
    ],
    "receptiarea": [
        "receptiarea (obj179)"
    ],
    "dome center": [
        "dome center (obj113)"
    ],
    "southeast porch": [
        "southeast porch (obj125)"
    ],
    "storage room": [
        "storage room (obj192)"
    ],
    "aquadome office": [
        "aquadome office (obj122)",
        "southeast porch (obj125)"
    ],
    "workshop": [
        "workshop (obj137)"
    ],
    "northwest porch": [
        "northwest porch (obj140)"
    ],
    "southwest porch": [
        "southwest porch (obj152)"
    ]
}